Elscript/Esformat.py
Elscript/Eslexer.py
Elscript/Esparser.py
Elscript/__init__.py
Elscript-0.0.1.dist-info/METADATA
Elscript-0.0.1.dist-info/WHEEL
Elscript-0.0.1.dist-info/top_level.txt
Elscript-0.0.1.dist-info/RECORD
