Metadata-Version: 2.1
Name: Elscript
Version: 0.0.1
Summary: eliot programming language
Home-page: UNKNOWN
Author: Kabuye Rogers
Author-email: <eliotscript1@gmail.com>
License: UNKNOWN
Keywords: Runtime,Console,Interpreter
Platform: UNKNOWN
Classifier: Development Status :: 1 - Planning
Classifier: Intended Audience :: Developers
Classifier: Programming Language :: Python :: 3
Classifier: Operating System :: Unix
Classifier: Operating System :: MacOS :: MacOS X
Classifier: Operating System :: Microsoft :: Windows
Requires-Dist: colorama
